Metadata-Version: 1.0
Name: distribpy
Version: 0.2
Summary: Gaussian distributions
Home-page: UNKNOWN
Author: Rasik Kane
Author-email: rasik.kane@gmail.com
License: UNKNOWN
Platform: UNKNOWN
